Metadata-Version: 2.4
Name: LAMAReg
Version: 1.4.0
Summary: Label Augmented Modality Agnostic Registration: A Python-based workflow combining deep learning-based segmentation and numerical solutions to generate precise warpfields between different MRI modalities.
Author-email: Ian Goodall-Halliwell <goodallhalliwell@gmail.com>
License-Expression: CC-BY-NC-4.0
Project-URL: Homepage, https://github.com/MICA-MNI/LAMAReg
Project-URL: Issues, https://github.com/MICA-MNI/LAMAReg/issues
Classifier: Programming Language :: Python :: 3
Classifier: Operating System :: OS Independent
Requires-Python: >=3.10
License-File: LICENSE
Requires-Dist: absl-py
Requires-Dist: antspyx
Requires-Dist: astunparse
Requires-Dist: certifi
Requires-Dist: charset-normalizer
Requires-Dist: colorama
Requires-Dist: cycler
Requires-Dist: flatbuffers
Requires-Dist: fonttools
Requires-Dist: gast
Requires-Dist: google-pasta
Requires-Dist: grpcio
Requires-Dist: h5py
Requires-Dist: idna
Requires-Dist: importlib_resources
Requires-Dist: keras
Requires-Dist: kiwisolver
Requires-Dist: libclang
Requires-Dist: markdown
Requires-Dist: markdown-it-py
Requires-Dist: MarkupSafe
Requires-Dist: matplotlib
Requires-Dist: mdurl
Requires-Dist: namex
Requires-Dist: nibabel
Requires-Dist: numpy
Requires-Dist: opt_einsum
Requires-Dist: optree
Requires-Dist: packaging
Requires-Dist: pandas
Requires-Dist: patsy
Requires-Dist: pillow
Requires-Dist: protobuf
Requires-Dist: Pygments
Requires-Dist: pyparsing
Requires-Dist: python-dateutil
Requires-Dist: pytz
Requires-Dist: PyYAML
Requires-Dist: requests
Requires-Dist: rich
Requires-Dist: scipy
Requires-Dist: six
Requires-Dist: statsmodels
Requires-Dist: tensorboard
Requires-Dist: tensorboard-data-server
Requires-Dist: tensorflow
Requires-Dist: termcolor
Requires-Dist: typing_extensions
Requires-Dist: tzdata
Requires-Dist: urllib3
Requires-Dist: webcolors
Requires-Dist: Werkzeug
Requires-Dist: wrapt
Dynamic: license-file
